CHANGELOG.txt
LICENCE.txt
MANIFEST.in
README.txt
setup.py
Chemo_Genius_Explorer/___init__.py
Chemo_Genius_Explorer.egg-info/PKG-INFO
Chemo_Genius_Explorer.egg-info/SOURCES.txt
Chemo_Genius_Explorer.egg-info/dependency_links.txt
Chemo_Genius_Explorer.egg-info/requires.txt
Chemo_Genius_Explorer.egg-info/top_level.txt